exports/__init__.py
exports/py.typed
python_exports-1.3.0.dist-info/licenses/LICENSE
python_exports-1.3.0.dist-info/WHEEL
python_exports-1.3.0.dist-info/METADATA
python_exports-1.3.0.dist-info/RECORD
