Metadata-Version: 2.4
Name: python-exports
Version: 1.3.0
Summary: @export decorator that adds a function or class to __all__
Author: Joren Hammudoglu
Author-email: Joren Hammudoglu <jhammudoglu@gmail.com>
License-Expression: BSD-3-Clause
License-File: LICENSE
Classifier: Development Status :: 5 - Production/Stable
Classifier: Operating System :: OS Independent
Classifier: Programming Language :: Python :: 3.10
Classifier: Programming Language :: Python :: 3.11
Classifier: Programming Language :: Python :: 3.12
Classifier: Programming Language :: Python :: 3.13
Classifier: Programming Language :: Python :: 3.14
Classifier: Typing :: Typed
Requires-Python: >=3.10
Project-URL: Changelog, https://github.com/jorenham/exports/releases
Project-URL: Documentation, https://github.com/jorenham/exports/blob/master/README.md
Project-URL: Funding, https://github.com/sponsors/jorenham
Project-URL: Issues, https://github.com/jorenham/exports/issues
Project-URL: Repository, https://github.com/jorenham/exports
